DCD_sentiment_analyser/SentimentAnalyser.py
DCD_sentiment_analyser/__init__.py
dcd_sentiment_analyser-0.1.2.dist-info/LICENSE
dcd_sentiment_analyser-0.1.2.dist-info/METADATA
dcd_sentiment_analyser-0.1.2.dist-info/WHEEL
dcd_sentiment_analyser-0.1.2.dist-info/top_level.txt
dcd_sentiment_analyser-0.1.2.dist-info/RECORD
