Metadata-Version: 2.1
Name: dcd-sentiment-analyser
Version: 0.1.2
Summary: sentiment analysis for dcd
Author-email: Younghangx <younghangx@163.com>
License: MIT License
Classifier: Programming Language :: Python :: 3
Classifier: License :: OSI Approved :: MIT License
Classifier: Operating System :: OS Independent
Requires-Python: >=3.8
License-File: LICENSE
Requires-Dist: torch >=2.0.1
Requires-Dist: transformers >=4.41.2
